shiftersummary/__init__.py
shiftersummary/command_line.py
shiftsum-0.2.dev2.dist-info/DESCRIPTION.rst
shiftsum-0.2.dev2.dist-info/METADATA
shiftsum-0.2.dev2.dist-info/RECORD
shiftsum-0.2.dev2.dist-info/WHEEL
shiftsum-0.2.dev2.dist-info/entry_points.txt
shiftsum-0.2.dev2.dist-info/metadata.json
shiftsum-0.2.dev2.dist-info/top_level.txt
shiftsummary/__init__.py
shiftsummary/command_line.py
