Metadata-Version: 2.0
Name: shiftsum
Version: 0.2.dev2
Summary: UNKNOWN
Home-page: https://github.com/Kecksdose/shiftsum
Author: Timon Schmelzer
Author-email: tisch1990@icloud.com
License: MIT
Keywords: lhcb shift datamanager shiftleader
Platform: UNKNOWN
Classifier: Development Status :: 3 - Alpha
Classifier: License :: OSI Approved :: MIT License
Classifier: Programming Language :: Python :: 3.6
Requires-Python: >=3.6
Requires-Dist: matplotlib
Requires-Dist: pandas
